tc_prometheus/__init__.py
tc_prometheus/metrics/__init__.py
tc_prometheus/metrics/prometheus_metrics.py
tc_prometheus-4.0.0.dist-info/licenses/LICENSE
tc_prometheus-4.0.0.dist-info/METADATA
tc_prometheus-4.0.0.dist-info/WHEEL
tc_prometheus-4.0.0.dist-info/top_level.txt
tc_prometheus-4.0.0.dist-info/RECORD
