Metadata-Version: 2.4
Name: tc_prometheus
Version: 4.0.0
Summary: Thumbor Prometheus metrics extension
Author-email: Simon Effenberg <savar@schuldeigen.de>
License-Expression: MIT
Classifier: Development Status :: 5 - Production/Stable
Classifier: Intended Audience :: Developers
Classifier: Natural Language :: English
Classifier: Operating System :: MacOS
Classifier: Operating System :: POSIX :: Linux
Classifier: Programming Language :: Python :: 3
License-File: LICENSE
Requires-Dist: prometheus_client==0.*,>=0.14.1
Requires-Dist: thumbor==7.*,>=7.7.5
Provides-Extra: all
Requires-Dist: prometheus_client==0.*,>=0.14.1; extra == "all"
Requires-Dist: thumbor==7.*,>=7.7.5; extra == "all"
Provides-Extra: tests
Requires-Dist: preggy==1.*,>=1.4.4; extra == "tests"
Requires-Dist: prometheus_client==0.*,>=0.14.1; extra == "tests"
Requires-Dist: pytest-cov==5.*,>=5.0.0; extra == "tests"
Requires-Dist: pytest==8.*,>=8.0.0; extra == "tests"
Requires-Dist: thumbor==7.*,>=7.7.5; extra == "tests"
Dynamic: license-file
